[
{
    "model": "auth.group",
    "pk": 1,
    "fields": {
        "name": "Project Manager",
        "permissions": [
            [
                "user_list_view",
                "accounts",
                "profile"
            ],
            [
                "add_project",
                "webapp",
                "project"
            ],
            [
                "add_user_in_project",
                "webapp",
                "project"
            ],
            [
                "change_project",
                "webapp",
                "project"
            ],
            [
                "delete_project",
                "webapp",
                "project"
            ],
            [
                "add_task",
                "webapp",
                "task"
            ],
            [
                "change_task",
                "webapp",
                "task"
            ],
            [
                "delete_task",
                "webapp",
                "task"
            ]
        ]
    }
},
{
    "model": "auth.group",
    "pk": 2,
    "fields": {
        "name": "Team Lead",
        "permissions": [
            [
                "user_list_view",
                "accounts",
                "profile"
            ],
            [
                "add_user_in_project",
                "webapp",
                "project"
            ],
            [
                "add_task",
                "webapp",
                "task"
            ],
            [
                "change_task",
                "webapp",
                "task"
            ],
            [
                "delete_task",
                "webapp",
                "task"
            ]
        ]
    }
},
{
    "model": "auth.group",
    "pk": 3,
    "fields": {
        "name": "Developer",
        "permissions": [
            [
                "add_task",
                "webapp",
                "task"
            ],
            [
                "change_task",
                "webapp",
                "task"
            ],
            [
                "delete_task",
                "webapp",
                "task"
            ]
        ]
    }
},
{
    "model": "auth.user",
    "pk": 1,
    "fields": {
        "password": "pbkdf2_sha256$390000$OgNTzvNGTWtFExAaKwtTtA$lIVZZuY43WB69VuseiU4lQTYZVK/7hHqu24FTiErKj8=",
        "last_login": "2023-01-02T13:00:44Z",
        "is_superuser": true,
        "username": "admin",
        "first_name": "admin",
        "last_name": "",
        "email": "admin@gmail.com",
        "is_staff": true,
        "is_active": true,
        "date_joined": "2022-12-05T14:42:49Z",
        "groups": [],
        "user_permissions": []
    }
},
{
    "model": "auth.user",
    "pk": 3,
    "fields": {
        "password": "pbkdf2_sha256$390000$0OtdQX0wl4iVHJBaec3gRx$LARS1rKsDVYyhZH25WzpXJR/u007Y2pDmNUCY5jqric=",
        "last_login": "2023-01-02T13:00:02Z",
        "is_superuser": false,
        "username": "developer1",
        "first_name": "developer1",
        "last_name": "",
        "email": "developer1@gmail.com",
        "is_staff": false,
        "is_active": true,
        "date_joined": "2022-12-23T03:49:53Z",
        "groups": [
            [
                "Developer"
            ]
        ],
        "user_permissions": []
    }
},
{
    "model": "auth.user",
    "pk": 4,
    "fields": {
        "password": "pbkdf2_sha256$390000$khZyOA9U1Pl5mmqlv2UCvt$JuzQHO8xYBDUM4akchu8a2oLfcq2kjoP8iZUA1fWeLQ=",
        "last_login": "2023-01-03T11:18:18Z",
        "is_superuser": false,
        "username": "projectmanager1",
        "first_name": "projectmanager1",
        "last_name": "",
        "email": "projectmanager1@gmail.com",
        "is_staff": false,
        "is_active": true,
        "date_joined": "2022-12-23T05:16:17Z",
        "groups": [
            [
                "Project Manager"
            ]
        ],
        "user_permissions": []
    }
},
{
    "model": "auth.user",
    "pk": 5,
    "fields": {
        "password": "pbkdf2_sha256$390000$cCaMaHg9r9miuSA5JwO1Hw$9QRaGvAlTpwIYJ8H+tgIWxKTrZDok+6PbG2+3IbXF3A=",
        "last_login": "2023-01-02T13:01:46Z",
        "is_superuser": false,
        "username": "teamlead1",
        "first_name": "teamlead1",
        "last_name": "",
        "email": "teamlead1@gmail.com",
        "is_staff": false,
        "is_active": true,
        "date_joined": "2022-12-23T05:32:10Z",
        "groups": [
            [
                "Team Lead"
            ]
        ],
        "user_permissions": []
    }
},
{
    "model": "auth.user",
    "pk": 7,
    "fields": {
        "password": "pbkdf2_sha256$390000$3AlmlbOcZ9KBpL7MJgegcn$kQ7aWqZ40hBOZ4QFA9t91T7wg9Ts7KOWeuqs2axZyLQ=",
        "last_login": "2023-01-03T11:24:14Z",
        "is_superuser": false,
        "username": "user",
        "first_name": "user",
        "last_name": "",
        "email": "user@gmail.com",
        "is_staff": false,
        "is_active": true,
        "date_joined": "2023-01-03T11:24:14Z",
        "groups": [],
        "user_permissions": []
    }
},
{
    "model": "auth.user",
    "pk": 8,
    "fields": {
        "password": "pbkdf2_sha256$390000$JrRx0XNtMPoTj9O0OwSqen$swvKO1Crx1DZkc0YP5dL1XBbRvJ8onKVXQOHML5U0DQ=",
        "last_login": "2023-01-03T11:26:27Z",
        "is_superuser": false,
        "username": "developer2",
        "first_name": "developer2",
        "last_name": "",
        "email": "developer2@gmail.com",
        "is_staff": false,
        "is_active": true,
        "date_joined": "2023-01-03T11:26:26Z",
        "groups": [
            [
                "Developer"
            ]
        ],
        "user_permissions": []
    }
},
{
    "model": "auth.user",
    "pk": 9,
    "fields": {
        "password": "pbkdf2_sha256$390000$c8aO0Bpy1Fq5fotVb013p6$Ev/VXkDPutUSDzU/vmv3J6QFGQXZENLdpuIPruISAVg=",
        "last_login": "2023-01-03T11:26:45Z",
        "is_superuser": false,
        "username": "teamlead2",
        "first_name": "teamlead2",
        "last_name": "",
        "email": "teamlead2@gmail.com",
        "is_staff": false,
        "is_active": true,
        "date_joined": "2023-01-03T11:26:45Z",
        "groups": [
            [
                "Team Lead"
            ]
        ],
        "user_permissions": []
    }
},
{
    "model": "auth.user",
    "pk": 10,
    "fields": {
        "password": "pbkdf2_sha256$390000$ckL9w6jEOAuDZNjpZQruOm$JFRn5i3MNgVViAUG3H8EXix04w5pdI7uq84iu4cB//M=",
        "last_login": "2023-01-03T11:27:01Z",
        "is_superuser": false,
        "username": "teamlead3",
        "first_name": "teamlead3",
        "last_name": "",
        "email": "teamlead3@gmail.com",
        "is_staff": false,
        "is_active": true,
        "date_joined": "2023-01-03T11:27:01Z",
        "groups": [
            [
                "Team Lead"
            ]
        ],
        "user_permissions": []
    }
},
{
    "model": "auth.user",
    "pk": 11,
    "fields": {
        "password": "pbkdf2_sha256$390000$khegre8UxAEqTtSf8RfMhG$288I7G5+ZitwcLZ5ZIGthTbxWT32cWky5+CO1Wnux1Y=",
        "last_login": "2023-01-03T11:27:16Z",
        "is_superuser": false,
        "username": "projectmanager2",
        "first_name": "projectmanager2",
        "last_name": "",
        "email": "projectmanager2@gmail.com",
        "is_staff": false,
        "is_active": true,
        "date_joined": "2023-01-03T11:27:16Z",
        "groups": [
            [
                "Project Manager"
            ]
        ],
        "user_permissions": []
    }
},
{
    "model": "auth.user",
    "pk": 12,
    "fields": {
        "password": "pbkdf2_sha256$390000$fseVE9vgEkvDzci5TvfJj4$WbrvwjHmcCkPkhVaJLU3/J+aa2oNPT7LtlIFXnjIk5o=",
        "last_login": "2023-01-03T11:27:45Z",
        "is_superuser": false,
        "username": "projectmanager3",
        "first_name": "projectmanager3",
        "last_name": "",
        "email": "projectmanager3@gmail.com",
        "is_staff": false,
        "is_active": true,
        "date_joined": "2023-01-03T11:27:45Z",
        "groups": [
            [
                "Project Manager"
            ]
        ],
        "user_permissions": []
    }
}
]
